http2py/__init__.py
http2py/authentication.py
http2py/cli_maker.py
http2py/client.py
http2py/decorators.py
http2py/default_configs.py
http2py/example_cli.py
http2py/example_osys_cli.py
http2py/global_state.py
http2py/http2py_cls.py
http2py/py2request.py
http2py/testing_utils.py
http2py/util.py
http2py-0.1.2.dist-info/LICENSE
http2py-0.1.2.dist-info/METADATA
http2py-0.1.2.dist-info/WHEEL
http2py-0.1.2.dist-info/top_level.txt
http2py-0.1.2.dist-info/RECORD
