Metadata-Version: 2.1
Name: http2py
Version: 0.1.2
Summary: Tools to create python binders to http web services.
Home-page: https://github.com/i2mint/http2py
Author: Thor Whalen
License: Apache
Keywords: webservice,http,requests,API
Platform: UNKNOWN
Classifier: Development Status :: 3 - Alpha
Classifier: Intended Audience :: Developers
Classifier: Topic :: Software Development
Classifier: License :: OSI Approved :: Apache Software License
Classifier: Programming Language :: Python :: 3.7
Requires-Dist: requests
